mcp_sqlite_server_d/__init__.py
mcp_sqlite_server_d/main.py
mcp_sqlite_server_d/mcp_sqlite_server_d.py
mcp_sqlite_server_d-0.1.0.dist-info/METADATA
mcp_sqlite_server_d-0.1.0.dist-info/WHEEL
mcp_sqlite_server_d-0.1.0.dist-info/entry_points.txt
mcp_sqlite_server_d-0.1.0.dist-info/RECORD
